neural_lam-0.5.0.dist-info/METADATA
neural_lam-0.5.0.dist-info/WHEEL
neural_lam-0.5.0.dist-info/entry_points.txt
neural_lam-0.5.0.dist-info/licenses/LICENSE.txt
neural_lam/__init__.py
neural_lam/config.py
neural_lam/create_graph.py
neural_lam/custom_loggers.py
neural_lam/datastore/__init__.py
neural_lam/datastore/base.py
neural_lam/datastore/mdp.py
neural_lam/datastore/npyfilesmeps/__init__.py
neural_lam/datastore/npyfilesmeps/compute_standardization_stats.py
neural_lam/datastore/npyfilesmeps/config.py
neural_lam/datastore/npyfilesmeps/store.py
neural_lam/datastore/plot_example.py
neural_lam/interaction_net.py
neural_lam/loss_weighting.py
neural_lam/metrics.py
neural_lam/models/__init__.py
neural_lam/models/ar_model.py
neural_lam/models/base_graph_model.py
neural_lam/models/base_hi_graph_model.py
neural_lam/models/graph_lam.py
neural_lam/models/hi_lam.py
neural_lam/models/hi_lam_parallel.py
neural_lam/plot_graph.py
neural_lam/train_model.py
neural_lam/utils.py
neural_lam/vis.py
neural_lam/weather_dataset.py
neural_lam-0.5.0.dist-info/RECORD
