Metadata-Version: 2.1
Name: neural-lam
Version: 0.5.0
Summary: LAM-based data-driven forecasting
Author-Email: Joel Oskarsson <joel.oskarsson@outlook.com>, Simon Adamov <Simon.Adamov@meteoswiss.ch>, Leif Denby <lcd@dmi.dk>, Simon Kamuk Christiansen <skc@dmi.dk>, Kasper Hintz <kah@dmi.dk>, Erik Larsson <erik.larsson@liu.se>, Hauke Schulz <has@dmi.dk>, Daniel Holmberg <daniel.holmberg@helsinki.fi>
Requires-Python: >=3.9
Requires-Dist: numpy>=1.24.2
Requires-Dist: wandb>=0.13.10
Requires-Dist: scipy>=1.10.0
Requires-Dist: pytorch-lightning>=2.0.3
Requires-Dist: shapely>=2.0.1
Requires-Dist: networkx>=3.0
Requires-Dist: Cartopy>=0.22.0
Requires-Dist: pyproj>=3.4.1
Requires-Dist: tueplots>=0.0.8
Requires-Dist: matplotlib>=3.7.0
Requires-Dist: plotly>=5.15.0
Requires-Dist: torch>=2.3.0
Requires-Dist: torch-geometric==2.3.1
Requires-Dist: parse>=1.20.2
Requires-Dist: dataclass-wizard<0.31.0
Requires-Dist: mllam-data-prep>=0.5.0
Requires-Dist: mlflow>=2.16.2
Requires-Dist: boto3>=1.35.32
Requires-Dist: nvidia-ml-py>=13.580.82
Provides-Extra: dev
Requires-Dist: pre-commit>=3.8.0; extra == "dev"
Requires-Dist: pytest>=8.3.2; extra == "dev"
Requires-Dist: pooch>=1.8.2; extra == "dev"
